estudo_python-1.0.1.data/data/pkg_proj/dados.json
pkg_proj/__init__.py
pkg_proj/__main__.py
pkg_proj/meuprograma.py
pkg_proj/rodaprograma.py
estudo_python-1.0.1.dist-info/METADATA
estudo_python-1.0.1.dist-info/WHEEL
estudo_python-1.0.1.dist-info/top_level.txt
estudo_python-1.0.1.dist-info/RECORD
