Metadata-Version: 2.1
Name: estudo-python
Version: 1.0.1
Summary: Exemplo para o Python
Home-page: http://www.aprendacodigo.com
Author: Aprenda Código
Author-email: contato@aprendacodigo.com
License: MIT
Keywords: exemplo tutorial desenvolvimento
Platform: UNKNOWN
Classifier: Development Status :: 4 - Beta
Classifier: Intended Audience :: Developers
Classifier: Topic :: Education :: Testing
Classifier: License :: OSI Approved :: MIT License
Classifier: Programming Language :: Python :: 3
Classifier: Programming Language :: Python :: 3.2
Classifier: Programming Language :: Python :: 3.3
Classifier: Programming Language :: Python :: 3.4
Classifier: Programming Language :: Python :: 3.7
Requires-Dist: sh (>=1.11)
